{
  "id": "3",
  "investigation": "exploding-stars",
  "order": "03",
  "title": "Blinking Supernovae",
  "slug": "blinking-supernovae/",
  "previous": {"title": "Discovering Supernovae", "link": "/discovering-supernovae/"},
  "next": {"title": "Describing Light Curves", "link": "/describe-light-curve/"},
  "layout": "TwoCol",
  "content": "<p>The two images below show a supernova discovered in the galaxy NGC 6946. The first image was taken before the explosion and the second was taken afterwards. Blink the two images and look for the supernova, which appears as a bright star in one image but not the other. When you spot the supernova, click on it.</p>",
  "widget": {
    "type": "SupernovaSelectorWithLightCurve",
    "source": "ZTF19abqmpsr",
    "options": {
      "showSelector": true,
      "showLightCurve": false,
      "autoplay": false,
      "toggleDataPointsVisibility": "50"
    }
  },
  "questionsByPage": [
    {
      "question": [
        {
          "id": "50",
          "questionType": "accordion",
          "tool": "selection",
          "title": "Question #1",
          "label": "<p>Click on a point on the Image to select the supernova</p>",
          "answerPre": "<span>Selected Supernova: </span>",
          "answerAccessor": "data"
        }
      ]
    }
  ]
}
