{
  "id": "coloring07",
  "investigation": "coloring-universe",
  "order": "070",
  "title": "Rubin Observatory LSST Camera Filters",
  "slug": "rubin-lsst-camera-filters/",
  "previous": {
    "title": "Eyes vs. Telescopes - Different Ways of Seeing",
    "link": "/eyes-vs-telescopes/"
  },
  "next": {
    "title": "Uses of Astronomical Filters",
    "link": "/uses-of-astronomical-filters/"
  },
  "images": [
    {
      "mediaPath": "/images/wavelength_ranges_of_visible_light.jpg",
      "altText": "Wavelength Ranges of Visible Light",
      "figText": "Comparison of visible color wavelength ranges with Rubin Observatory filters (nm = nanometers)",
      "layout": {
        "col": "left",
        "row": "middle"
      }
    }
  ],
  "layout": "SingleCol",
  "contents": [
    {
      "content": "<p>The Rubin Observatory LSST Camera contains six filters, identified by the letters u, g, r, i, z and y. Four of these filters (u, g, r, and i) transmit some visible light our eyes can see. The u filter also transmits ultraviolet light. The z and y filters transmit only infrared light. As you can see, these filters transmit light over a broader range of wavelengths and are not limited to just one color of light. You can remember these filters in their correct order from short wavelengths to long wavelengths by using the mnemonic “U-Grizy”.</p>",
      "layout": {
        "col": "left",
        "row": "top"
      }
    }
  ],
  "questionsByPage": [
    {
      "question": [
        {
          "id": "7a",
          "questionType": "compoundSelect",
          "compoundQuestion": ["7a", "7b"],
          "answerAccessor": "select",
          "options": [
            { "label": "u", "value": "u" },
            { "label": "g", "value": "g" },
            { "label": "r", "value": "r" },
            { "label": "i", "value": "i" },
            { "label": "z", "value": "z" },
            { "label": "y", "value": "y" }
          ],
          "title": "Question #1",
          "labelPre": "The ",
          "labelPost": "filter transmits the longest wavelengths of light",
          "srLabel": "...",
          "answerPre": "...",
          "answerPost": "...",
          "placeholder": "(u,g,r,i,z,y)"
        },
        {
          "id": "7b",
          "questionType": "compoundSelect",
          "compoundQuestion": ["7a", "7b"],
          "answerAccessor": "select",
          "options": [
            { "label": "infrared", "value": "infrared" },
            { "label": "visible", "value": "visible" },
            { "label": "ultraviolet", "value": "violet" }
          ],
          "title": "Question #1",
          "labelPre": "and what form of light is it?",
          "labelPost": "",
          "srLabel": "...",
          "answerPre": "...",
          "answerPost": "...",
          "placeholder": "(infrared, visible or ultraviolet)"
        }
      ]
    },
    {
      "question": [
        {
          "id": "8a",
          "questionType": "compoundSelect",
          "compoundQuestion": ["8a", "8b"],
          "answerAccessor": "select",
          "options": [
            { "label": "u", "value": "u" },
            { "label": "g", "value": "g" },
            { "label": "r", "value": "r" },
            { "label": "i", "value": "i" },
            { "label": "z", "value": "z" },
            { "label": "y", "value": "y" }
          ],
          "title": "Question #1",
          "labelPre": "The ",
          "labelPost": "filter transmits the shortest wavelengths of light",
          "srLabel": "...",
          "answerPre": "...",
          "answerPost": "...",
          "placeholder": "(u,g,r,i,z,y)"
        },
        {
          "id": "8b",
          "questionType": "compoundSelect",
          "compoundQuestion": ["8a", "8b"],
          "answerAccessor": "select",
          "options": [
            { "label": "infrared", "value": "infrared" },
            { "label": "visible", "value": "visible" },
            { "label": "ultraviolet", "value": "violet" }
          ],
          "title": "Question #1",
          "labelPre": "and what form of light is it?",
          "labelPost": "",
          "srLabel": "...",
          "answerPre": "...",
          "answerPost": "...",
          "placeholder": "(infrared, visible or ultraviolet)"
        }
      ]
    },
    {
      "question": [
        {
          "id": "9",
          "questionType": "multiSelect",
          "title": "Question #1",
          "labelPre": "What two filters transmit green light?",
          "labelPost": "",
          "options": [
            { "label": "u", "value": "u" },
            { "label": "g", "value": "g" },
            { "label": "r", "value": "r" },
            { "label": "i", "value": "i" },
            { "label": "z", "value": "z" },
            { "label": "y", "value": "y" }
          ],
          "placeholder": "Select",
          "answerPre": "<p>Selected: </p>",
          "answerAccessor": "multi-select"
        }
      ]
    },
    {
      "question": [
        {
          "id": "10",
          "title": "Question #1",
          "questionType": "multiSelect",
          "answerAccessor": "multi-select",
          "labelPre": "What four colors of light are transmitted by the r filter?",
          "labelPost": "",
          "options": [
            { "label": "violet", "value": "violet" },
            { "label": "blue", "value": "blue" },
            { "label": "green", "value": "green" },
            { "label": "yellow", "value": "yellow" },
            { "label": "orange", "value": "orange" },
            { "label": "red", "value": "red" }
          ],
          "placeholder": "Select",
          "answerPre": "<p>Selected: </p>"
        }
      ]
    },
    {
      "question": [
        {
          "id": "11",
          "title": "Question #1",
          "questionType": "multiSelect",
          "answerAccessor": "multi-select",
          "labelPre": "What two filters transmit both visible and invisible light?",
          "labelPost": "",
          "options": [
            { "label": "u", "value": "u" },
            { "label": "g", "value": "g" },
            { "label": "r", "value": "r" },
            { "label": "i", "value": "i" },
            { "label": "z", "value": "z" },
            { "label": "y", "value": "y" }
          ],
          "placeholder": "Select",
          "answerPre": "<p>Selected: </p>"
        }
      ]
    }
  ]
}
